connect6/__init__.py
connect6/__main__.py
connect6/env.py
connect6/game.py
connect6/version.py
connect6-0.0.1.dist-info/LICENSE
connect6-0.0.1.dist-info/METADATA
connect6-0.0.1.dist-info/WHEEL
connect6-0.0.1.dist-info/top_level.txt
connect6-0.0.1.dist-info/RECORD
