Metadata-Version: 2.1
Name: connect6
Version: 0.0.1
Summary: A Python library for developing Connect6 AI algorithms
Home-page: https://github.com/sjjeong94/connect6
Author: sjjeong94
Author-email: sjjeong94@gmail.com
License: MIT
Platform: UNKNOWN
License-File: LICENSE
Requires-Dist: numpy
Requires-Dist: pygame
